spider_rs-0.0.56.dist-info/METADATA
spider_rs-0.0.56.dist-info/WHEEL
spider_rs-0.0.56.dist-info/licenses/LICENSE.txt
spider_rs/__init__.py
spider_rs/spider_rs.cpython-313-darwin.so
spider_rs-0.0.56.dist-info/RECORD
