Metadata-Version: 2.4
Name: spider_rs
Version: 0.0.56
Classifier: Programming Language :: Rust
Classifier: Programming Language :: Python :: Implementation :: CPython
Classifier: Programming Language :: Python :: Implementation :: PyPy
License-File: LICENSE.txt
Summary: The fastest web crawler and indexer.
License: MIT
Requires-Python: >=3.7
Project-URL: Source Code, https://github.com/spider-rs/spider-py
